{
    "pred_continue": [
        {
            "heading": [
                "Current",
                "20pips",
                "40pips"
            ]
        },
        {
            "item": {
                "-25<": [
                    38.79,
                    47.07,
                    45.51
                ],
                "-20": [
                    27.0,
                    25.28,
                    27.71
                ],
                "-5": [
                    10.75,
                    11.33,
                    9.58
                ],
                "5": [
                    12.16,
                    6.7,
                    6.29
                ],
                "20": [
                    9.2,
                    7.98,
                    9.21
                ],
                ">25": [
                    2.09,
                    1.64,
                    1.7
                ],
                "Potential Trade": [
                    "Sell target:  -25<",
                    "Sell target:  -25<",
                    "Sell target:  -25<"
                ]
            }
        }
    ]
}