{
    "pred_continue": [
        {
            "date": "11-05-2024 00:51:10"
        },
        {
            "heading": [
                "Current",
                "10pips Continue",
                "20pips Continue"
            ]
        },
        {
            "item": {
                "-10": [
                    6.82,
                    16.92,
                    27.82
                ],
                "-5": [
                    9.96,
                    33.59,
                    28.6
                ],
                "-1": [
                    11.49,
                    32.32,
                    27.61
                ],
                "1": [
                    25.62,
                    6.25,
                    4.59
                ],
                "5": [
                    28.01,
                    6.91,
                    4.89
                ],
                "10": [
                    18.1,
                    4.01,
                    6.5
                ],
                "Potential Trade": [
                    "Buy target: 5",
                    "Sell target: -5",
                    "Sell target: -5"
                ]
            }
        },
        {
            "extra": {
                "trade_type": [
                    "Buy",
                    "Sell",
                    "Sell"
                ],
                "trade_target": [
                    "5",
                    "-5",
                    "-5"
                ]
            }
        },
        {
            "bb4_results": {
                "upper_bb4": [
                    150.97193840055493,
                    150.97193840055493,
                    150.97193840055493
                ],
                "lower_bb4": [
                    145.563161599445,
                    145.563161599445,
                    145.563161599445
                ]
            }
        }
    ]
}