{
    "pred_variability": [
        {
            "date": "10-03-2024 19:37:30"
        },
        {
            "heading": [
                "10pips",
                "-10pips"
            ]
        },
        {
            "item": {
                "-10": [
                    25.29,
                    25.29
                ],
                "-5": [
                    31.2,
                    31.2
                ],
                "-1": [
                    34.56,
                    34.56
                ],
                "1": [
                    3.81,
                    3.81
                ],
                "5": [
                    3.82,
                    3.82
                ],
                "10": [
                    1.33,
                    1.33
                ],
                "Potential Trade": [
                    "Sell target: -1",
                    "Sell target: -1"
                ]
            }
        },
        {
            "extra": {
                "Trade Type": [
                    "Sell",
                    "Sell"
                ],
                "Trade Target": [
                    "-1",
                    "-1"
                ]
            }
        }
    ]
}