{
    "pred_variability": [
        {
            "date": "21-02-2024 20:16:06"
        },
        {
            "heading": [
                "10pips",
                "-10pips"
            ]
        },
        {
            "item": {
                "-25": [
                    28.91,
                    31.94
                ],
                "-20": [
                    12.08,
                    14.11
                ],
                "-10": [
                    20.29,
                    21.06
                ],
                "10": [
                    16.43,
                    14.11
                ],
                "20": [
                    15.25,
                    12.91
                ],
                "25": [
                    7.04,
                    5.87
                ],
                "Potential Trade": [
                    "Sell target:  -25",
                    "Sell target:  -25"
                ]
            }
        }
    ]
}